{
  "Scene": "Urban",
  "TimeOfDay": "Daytime",
  "Weather": "Clear",
  "RoadConditions": "Dry",
  "LaneInformation": {
    "NumberOfLanes": "MultipleLanes",
    "LaneMarkings": "LaneVisible",
    "SpecialLanes": [
      "Crosswalk",
      "Bike Lane"
    ]
  },
  "TrafficSigns": {
    "TrafficLightState": "Red",
    "TrafficSignsTypes": [
      "Traffic Light",
      "Pedestrian Signal"
    ],
    "TrafficSignsVisibility": "Visible",
    "VehicleTypes": [
      "Van",
      "Sedan"
    ]
  },
  "Vehicles": {
    "TotalNumber": "MultipleVehicles",
    "InMotion": [
      "True"
    ],
    "States": [
      "In Motion"
    ]
  },
  "Pedestrians": [
    "Crossing Street"
  ],
  "Bicyclist": {
    "Presence": "True",
    "Location": "Crossing Road"
  },
  "Directionality": "Two-Way",
  "Visibility": {
    "General": "Good",
    "SpecificImpairments": [
      "Shadows"
    ]
  },
  "Ego-Vehicle": {
    "Direction": "EgoForward",
    "Maneuver": "EgoMoving"
  },
  "CameraCondition": "Clear",
  "Severity": 5
}