{
  "Scene": "Urban",
  "TimeOfDay": "Daytime",
  "Weather": "Sunny",
  "RoadConditions": "Dry",
  "LaneInformation": {
    "NumberOfLanes": "Four",
    "LaneMarkings": "LaneVisible",
    "SpecialLanes": [
      "NoSpecialLanes"
    ]
  },
  "TrafficSigns": {
    "TrafficLightState": "Red",
    "TrafficSignsTypes": [
      "Traffic Light",
      "Pedestrian Crossing"
    ],
    "TrafficSignsVisibility": "Visible",
    "VehicleTypes": [
      "Sedan"
    ]
  },
  "Vehicles": {
    "TotalNumber": "Few",
    "InMotion": [
      "False"
    ],
    "States": [
      "Stopped at Traffic Light"
    ]
  },
  "Pedestrians": [
    "Crossing Street"
  ],
  "Directionality": "Two-Way",
  "Ego-Vehicle": {
    "Direction": "EgoForward",
    "Maneuver": "EgoMoving"
  },
  "Visibility": {
    "General": "Good",
    "SpecificImpairments": [
      "NoImpairments"
    ]
  },
  "CameraCondition": "Clear",
  "Severity": 5
}