{
  "Scene": "Urban",
  "TimeOfDay": "Daytime",
  "Weather": "Sunny",
  "RoadConditions": "Dry",
  "LaneInformation": {
    "NumberOfLanes": "MultipleLanes",
    "LaneMarkings": "LaneVisible",
    "SpecialLanes": [
      "NoSpecialLanes"
    ]
  },
  "TrafficSigns": {
    "TrafficSignsTypes": [
      "NoTrafficSigns"
    ],
    "TrafficSignsVisibility": "SignNotVisible",
    "VehicleTypes": [
      "Sedan",
      "Sports Car",
      "Pickup Truck"
    ]
  },
  "Vehicles": {
    "TotalNumber": "MultipleVehicles",
    "InMotion": [
      "True"
    ],
    "States": [
      "Parked",
      "In Motion"
    ]
  },
  "Pedestrians": [
    "NoPed"
  ],
  "Directionality": "One-Way",
  "Ego-Vehicle": {
    "Direction": "Forward",
    "Maneuver": "Moving"
  },
  "Visibility": {
    "General": "Good",
    "SpecificImpairments": [
      "NoImpairments"
    ]
  },
  "CameraCondition": "Clear",
  "Severity": 2
}