{
  "Scene": "Intersection",
  "TimeOfDay": "Daytime",
  "Weather": "Overcast",
  "RoadConditions": "Dry",
  "LaneInformation": {
    "NumberOfLanes": "Two",
    "LaneMarkings": "LaneVisible",
    "SpecialLanes": [
      "Street Parking",
      "Crosswalk"
    ]
  },
  "TrafficSigns": {
    "TrafficLightState": "Red",
    "TrafficSignsTypes": [
      "Traffic Light",
      "No Parking",
      "Pedestrian Signal"
    ],
    "TrafficSignsVisibility": "Visible",
    "VehicleTypes": [
      "Hatchback",
      "Sedan",
      "Compact Car"
    ]
  },
  "Vehicles": {
    "TotalNumber": "MultipleVehicles",
    "InMotion": [
      "True"
    ],
    "States": [
      "Parked",
      "In Motion"
    ]
  },
  "Pedestrians": [
    "MultiplePed"
  ],
  "Bicyclist": {
    "Presence": "True",
    "Location": "In Vehicle Lane"
  },
  "Directionality": "Two-Way",
  "Visibility": {
    "General": "Good",
    "SpecificImpairments": [
      "NoImpairments"
    ]
  },
  "Ego-Vehicle": {
    "Direction": "EgoForward",
    "Maneuver": "EgoMoving"
  },
  "CameraCondition": "Clear",
  "Severity": 7
}