{
  "Scene": "Commercial",
  "TimeOfDay": "Daytime",
  "Weather": "Sunny",
  "RoadConditions": "Dry",
  "LaneInformation": {
    "NumberOfLanes": "Four",
    "LaneMarkings": "LaneVisible",
    "SpecialLanes": [
      "Bike Lane"
    ]
  },
  "TrafficSigns": {
    "TrafficSignsTypes": [
      "NoTrafficSigns"
    ],
    "TrafficSignsVisibility": "SignNotVisible",
    "VehicleTypes": [
      "Sedan",
      "SUV"
    ]
  },
  "Vehicles": {
    "TotalNumber": "MultipleVehicles",
    "InMotion": [
      "True"
    ],
    "States": [
      "In Motion",
      "Parked"
    ]
  },
  "Pedestrians": [
    "Visible on Sidewalk"
  ],
  "Directionality": "Two-Way",
  "Ego-Vehicle": {
    "Direction": "Forward",
    "Maneuver": "Moving"
  },
  "Visibility": {
    "General": "Good",
    "SpecificImpairments": [
      "Camera glare"
    ]
  },
  "CameraCondition": "Glare",
  "Severity": 2
}