{
  "Scene": "Urban",
  "TimeOfDay": "Daytime",
  "Weather": "Overcast",
  "RoadConditions": "Dry",
  "LaneInformation": {
    "NumberOfLanes": "Three",
    "LaneMarkings": "LaneVisible",
    "SpecialLanes": [
      "Left Turn Only Lane",
      "Construction Cones"
    ]
  },
  "TrafficSigns": {
    "TrafficSignsTypes": [
      "NoTrafficSigns"
    ],
    "TrafficSignsVisibility": "SignNotVisible",
    "VehicleTypes": [
      "Sedan",
      "SUV",
      "Delivery Truck"
    ]
  },
  "Vehicles": {
    "TotalNumber": "MultipleVehicles",
    "InMotion": [
      "False"
    ],
    "States": [
      "In Queue"
    ]
  },
  "Pedestrians": [
    "NoPed"
  ],
  "Directionality": "Two-Way",
  "Ego-Vehicle": {
    "Direction": "EgoForward",
    "Maneuver": "EgoIn Queue"
  },
  "Visibility": {
    "General": "Good",
    "SpecificImpairments": [
      "NoImpairments"
    ]
  },
  "CameraCondition": "Clear",
  "Severity": 5
}