{
  "Scene": "Commercial",
  "TimeOfDay": "Daytime",
  "Weather": "Partly Cloudy",
  "RoadConditions": "Dry",
  "LaneInformation": {
    "NumberOfLanes": "MultipleLanes",
    "LaneMarkings": "LaneVisible",
    "SpecialLanes": [
      "Right Turn Only Lane",
      "Left Turn Only Lane"
    ]
  },
  "TrafficSigns": {
    "TrafficLightState": "Red",
    "TrafficSignsTypes": [
      "Right Lane Must Turn Right",
      "Traffic Light"
    ],
    "TrafficSignsVisibility": "Visible",
    "VehicleTypes": [
      "Sedan",
      "Bus",
      "Cars"
    ]
  },
  "Vehicles": {
    "TotalNumber": "MultipleVehicles",
    "InMotion": [
      "False"
    ],
    "States": [
      "Stopped"
    ]
  },
  "Pedestrians": [
    "Visible on Sidewalk"
  ],
  "Directionality": "Two-Way",
  "Visibility": {
    "General": "Good",
    "SpecificImpairments": [
      "NoImpairments"
    ]
  },
  "Ego-Vehicle": {
    "Direction": "EgoStopped at Intersection",
    "Maneuver": "EgoWaiting"
  },
  "CameraCondition": "Clear",
  "Severity": 3
}