{
  "Scene": "Urban",
  "TimeOfDay": "Daytime",
  "Weather": "Clear",
  "RoadConditions": "Dry",
  "LaneInformation": {
    "NumberOfLanes": "Two",
    "LaneMarkings": "LaneVisible",
    "SpecialLanes": [
      "Forward Only Lane"
    ]
  },
  "TrafficSigns": {
    "TrafficLightState": "Green",
    "TrafficSignsTypes": [
      "No Turn On Red",
      "Traffic Light"
    ],
    "TrafficSignsVisibility": "Visible",
    "VehicleTypes": [
      "NoVehicleType"
    ]
  },
  "Vehicles": {
    "TotalNumber": "NoVehicle",
    "InMotion": [
      "False"
    ],
    "States": [
      "NoVehicleState"
    ]
  },
  "Pedestrians": [
    "NoPed"
  ],
  "Directionality": "Two-Way",
  "Ego-Vehicle": {
    "Direction": "EgoForward",
    "Maneuver": "EgoProceeding through Intersection"
  },
  "Visibility": {
    "General": "Good",
    "SpecificImpairments": [
      "NoImpairments"
    ]
  },
  "CameraCondition": "Clear",
  "Severity": 1
}