{
  "Scene": "Urban",
  "TimeOfDay": "Daytime",
  "Weather": "Clear",
  "RoadConditions": "Dry",
  "LaneInformation": {
    "NumberOfLanes": "MultipleLanes",
    "LaneMarkings": "LaneVisible",
    "SpecialLanes": [
      "Crosswalk"
    ]
  },
  "TrafficSigns": {
    "TrafficLightState": "Green",
    "TrafficSignsTypes": [
      "Traffic Light"
    ],
    "TrafficSignsVisibility": "Visible",
    "VehicleTypes": [
      "Truck",
      "Sedan",
      "SUV"
    ]
  },
  "Vehicles": {
    "TotalNumber": "MultipleVehicles",
    "InMotion": [
      "True"
    ],
    "States": [
      "In Motion"
    ]
  },
  "Pedestrians": [
    "Visible on Sidewalk"
  ],
  "Directionality": "Two-Way",
  "Ego-Vehicle": {
    "Direction": "EgoApproaching Intersection",
    "Maneuver": "EgoSlowing Down"
  },
  "Visibility": {
    "General": "Good",
    "SpecificImpairments": [
      "NoImpairments"
    ]
  },
  "CameraCondition": "Clear",
  "Severity": 4
}