{
  "Scene": "Industrial",
  "TimeOfDay": "Daytime",
  "Weather": "Overcast",
  "RoadConditions": "Dry",
  "LaneInformation": {
    "NumberOfLanes": "One",
    "LaneMarkings": "LaneVisible",
    "SpecialLanes": [
      "NoSpecialLanes"
    ]
  },
  "TrafficSigns": {
    "TrafficSignsTypes": [
      "NoTrafficSigns"
    ],
    "TrafficSignsVisibility": "SignNotVisible",
    "VehicleTypes": [
      "SUV",
      "Sedan"
    ]
  },
  "Vehicles": {
    "TotalNumber": "Few",
    "InMotion": [
      "False"
    ],
    "States": [
      "Parked"
    ]
  },
  "Pedestrians": [
    "NoPed"
  ],
  "Directionality": "One-Way",
  "Ego-Vehicle": {
    "Direction": "EgoForward",
    "Maneuver": "EgoMoving"
  },
  "Visibility": {
    "General": "Reduced",
    "SpecificImpairments": [
      "Shadows"
    ]
  },
  "CameraCondition": "Clear",
  "Severity": 5
}