{
  "Scene": "Urban",
  "TimeOfDay": "Daytime",
  "Weather": "Clear",
  "RoadConditions": "Dry",
  "LaneInformation": {
    "NumberOfLanes": "Two",
    "LaneMarkings": "LaneVisible",
    "SpecialLanes": [
      "NoSpecialLanes"
    ]
  },
  "TrafficSigns": {
    "TrafficSignsTypes": [
      "NoTrafficSigns"
    ],
    "TrafficSignsVisibility": "SignNotVisible",
    "VehicleTypes": [
      "Pickup Truck",
      "Sedan",
      "SUV",
      "Bus",
      "Commercial Delivery Truck"
    ]
  },
  "Vehicles": {
    "TotalNumber": "MultipleVehicles",
    "InMotion": [
      "True"
    ],
    "States": [
      "Parked",
      "In Motion",
      "Stopped at Intersection"
    ]
  },
  "Pedestrians": [
    "Visible on Sidewalk"
  ],
  "Directionality": "Two-Way",
  "Ego-Vehicle": {
    "Direction": "EgoForward",
    "Maneuver": "EgoMoving"
  },
  "Visibility": {
    "General": "Good",
    "SpecificImpairments": [
      "NoImpairments"
    ]
  },
  "CameraCondition": "Clear",
  "Severity": 3
}