{
  "Scene": "Urban",
  "TimeOfDay": "Dusk/Dawn",
  "Weather": "Clear",
  "RoadConditions": "Dry",
  "LaneInformation": {
    "NumberOfLanes": "Two",
    "LaneMarkings": "LaneVisible",
    "SpecialLanes": [
      "NoSpecialLanes"
    ]
  },
  "TrafficSigns": {
    "TrafficSignsTypes": [
      "NoTrafficSigns"
    ],
    "TrafficSignsVisibility": "SignNotVisible",
    "VehicleTypes": [
      "Construction Vehicles",
      "Sedan",
      "SUV"
    ]
  },
  "Vehicles": {
    "TotalNumber": "Few",
    "InMotion": [
      "True"
    ],
    "States": [
      "In Motion",
      "Parked"
    ]
  },
  "Pedestrians": [
    "NoPed"
  ],
  "Directionality": "Two-Way",
  "Ego-Vehicle": {
    "Direction": "Forward",
    "Maneuver": "Moving"
  },
  "Visibility": {
    "General": "Good"
  },
  "CameraCondition": "Clear",
  "Severity": 2
}